{
  "boxShadow": {
    "0": {
      "value": {
        "x": "0px",
        "y": "1px",
        "blur": "2px",
        "spread": "0px",
        "color": "#1319260d",
        "type": "dropShadow"
      },
      "type": "boxShadow"
    },
    "1": {
      "value": [
        {
          "color": "#1319260f",
          "type": "dropShadow",
          "x": "0px",
          "y": "1px",
          "blur": "2px",
          "spread": "0px"
        },
        {
          "color": "#1319261a",
          "type": "dropShadow",
          "x": "0px",
          "y": "1px",
          "blur": "3px",
          "spread": "0px"
        }
      ],
      "type": "boxShadow"
    },
    "2": {
      "value": [
        {
          "color": "#1319260f",
          "type": "dropShadow",
          "x": "0px",
          "y": "2px",
          "blur": "4px",
          "spread": "-2px"
        },
        {
          "color": "#1319261a",
          "type": "dropShadow",
          "x": "0px",
          "y": "4px",
          "blur": "8px",
          "spread": "-2px"
        }
      ],
      "type": "boxShadow"
    },
    "3": {
      "value": [
        {
          "color": "#13192608",
          "type": "dropShadow",
          "x": "0px",
          "y": "8px",
          "blur": "8px",
          "spread": "-4px"
        },
        {
          "color": "#13192614",
          "type": "dropShadow",
          "x": "0px",
          "y": "20px",
          "blur": "24px",
          "spread": "-4px"
        }
      ],
      "type": "boxShadow"
    },
    "4": {
      "value": [
        {
          "color": "#13192608",
          "type": "dropShadow",
          "x": "0px",
          "y": "4px",
          "blur": "6px",
          "spread": "-2px"
        },
        {
          "color": "#13192614",
          "type": "dropShadow",
          "x": "0px",
          "y": "12px",
          "blur": "16px",
          "spread": "-4px"
        }
      ],
      "type": "boxShadow"
    },
    "5": {
      "value": {
        "x": "0px",
        "y": "24px",
        "blur": "48px",
        "spread": "-12px",
        "color": "#1319262e",
        "type": "dropShadow"
      },
      "type": "boxShadow"
    },
    "6": {
      "value": {
        "x": "0px",
        "y": "32px",
        "blur": "64px",
        "spread": "-12px",
        "color": "#13192624",
        "type": "dropShadow"
      },
      "type": "boxShadow"
    },
    "none": {
      "value": {
        "x": "0px",
        "y": "0px",
        "blur": "0px",
        "spread": "0px",
        "color": "#00000000",
        "type": "dropShadow"
      },
      "type": "boxShadow"
    }
  },
  "lineHeights": {
    "2xs": {
      "value": "100%",
      "type": "lineHeights"
    },
    "sm": {
      "value": "125%",
      "type": "lineHeights"
    },
    "md": {
      "value": "135%",
      "type": "lineHeights"
    },
    "lg": {
      "value": "150%",
      "type": "lineHeights"
    },
    "xl": {
      "value": "170%",
      "type": "lineHeights"
    },
    "2xl": {
      "value": "200%",
      "type": "lineHeights"
    }
  },
  "fontSizes": {
    "2xs": {
      "value": "{fontSizes.base} * 0.625",
      "type": "fontSizes"
    },
    "xs": {
      "value": "{fontSizes.base} * 0.75",
      "type": "fontSizes"
    },
    "sm": {
      "value": "{fontSizes.base} * 0.875",
      "type": "fontSizes"
    },
    "base": {
      "value": "16",
      "type": "fontSizes"
    },
    "md": {
      "value": "{fontSizes.base} * 1.125",
      "type": "fontSizes"
    },
    "lg": {
      "value": "{fontSizes.base} * 1.25",
      "type": "fontSizes"
    },
    "xl": {
      "value": "{fontSizes.base} * 1.5",
      "type": "fontSizes"
    },
    "2xl": {
      "value": "{fontSizes.base} * 1.75",
      "type": "fontSizes"
    },
    "3xl": {
      "value": "{fontSizes.base} * 2",
      "type": "fontSizes"
    },
    "4xl": {
      "value": "{fontSizes.base} * 2.5",
      "type": "fontSizes"
    },
    "5xl": {
      "value": "{fontSizes.base} * 2.75",
      "type": "fontSizes"
    },
    "6xl": {
      "value": "{fontSizes.base} * 3",
      "type": "fontSizes"
    },
    "7xl": {
      "value": "{fontSizes.base} * 4",
      "type": "fontSizes"
    },
    "8xl": {
      "value": "{fontSizes.base} * 5.5",
      "type": "fontSizes"
    },
    "9xl": {
      "value": "{fontSizes.base} * 6",
      "type": "fontSizes"
    }
  },
  "letterSpacings": {
    "xs": {
      "value": "-2%",
      "type": "letterSpacing"
    },
    "sm": {
      "value": "-1%",
      "type": "letterSpacing"
    },
    "md": {
      "value": "0%",
      "type": "letterSpacing"
    },
    "lg": {
      "value": "1%",
      "type": "letterSpacing"
    },
    "xl": {
      "value": "2%",
      "type": "letterSpacing"
    }
  },
  "fontFamily": {
    "heading": {
      "value": "Poppins",
      "type": "fontFamilies"
    },
    "body": {
      "value": "Poppins",
      "type": "fontFamilies"
    },
    "mono": {
      "value": "SF Mono",
      "type": "fontFamilies"
    }
  },
  "fontWeights": {
    "hairline": {
      "value": "100",
      "type": "fontWeights"
    },
    "thin": {
      "value": "200",
      "type": "fontWeights"
    },
    "light": {
      "value": "300",
      "type": "fontWeights"
    },
    "normal": {
      "value": "400",
      "type": "fontWeights"
    },
    "medium": {
      "value": "500",
      "type": "fontWeights"
    },
    "semibold": {
      "value": "600",
      "type": "fontWeights"
    },
    "bold": {
      "value": "700",
      "type": "fontWeights"
    },
    "extrabold": {
      "value": "800",
      "type": "fontWeights"
    },
    "black": {
      "value": "900",
      "type": "fontWeights"
    }
  },
  "mobile": {
    "heading-mobile": {
      "bold": {
        "h6": {
          "value": {
            "fontFamily": "{fontFamily.heading}",
            "fontWeight": "{fontWeights.semibold}",
            "lineHeight": "{lineHeights.sm}",
            "fontSize": "{fontSizes.lg}",
            "letterSpacing": "{letterSpacings.md}",
            "paragraphSpacing": "",
            "textCase": "",
            "textDecoration": ""
          },
          "type": "typography"
        },
        "h5": {
          "value": {
            "fontFamily": "{fontFamily.heading}",
            "fontWeight": "{fontWeights.semibold}",
            "lineHeight": "{lineHeights.sm}",
            "fontSize": "{fontSizes.xl}",
            "letterSpacing": "{letterSpacings.md}",
            "paragraphSpacing": "",
            "textCase": "",
            "textDecoration": ""
          },
          "type": "typography"
        },
        "h4": {
          "value": {
            "fontFamily": "{fontFamily.heading}",
            "fontWeight": "{fontWeights.semibold}",
            "lineHeight": "{lineHeights.lg}",
            "fontSize": "{fontSizes.2xl}",
            "letterSpacing": "{letterSpacings.md}",
            "paragraphSpacing": "",
            "textCase": "",
            "textDecoration": ""
          },
          "type": "typography"
        },
        "h3": {
          "value": {
            "fontFamily": "{fontFamily.heading}",
            "fontWeight": "{fontWeights.semibold}",
            "lineHeight": "{lineHeights.lg}",
            "fontSize": "{fontSizes.3xl}",
            "letterSpacing": "{letterSpacings.md}",
            "paragraphSpacing": "",
            "textCase": "",
            "textDecoration": ""
          },
          "type": "typography"
        },
        "h2": {
          "value": {
            "fontFamily": "{fontFamily.heading}",
            "fontWeight": "{fontWeights.semibold}",
            "lineHeight": "{lineHeights.lg}",
            "fontSize": "{fontSizes.4xl}",
            "letterSpacing": "{letterSpacings.md}",
            "paragraphSpacing": "",
            "textCase": "",
            "textDecoration": ""
          },
          "type": "typography"
        },
        "h1": {
          "value": {
            "fontFamily": "{fontFamily.heading}",
            "fontWeight": "{fontWeights.semibold}",
            "lineHeight": "{lineHeights.lg}",
            "fontSize": "{fontSizes.5xl}",
            "letterSpacing": "{letterSpacings.md}",
            "paragraphSpacing": "",
            "textCase": "",
            "textDecoration": ""
          },
          "type": "typography"
        },
        "d2": {
          "value": {
            "fontFamily": "{fontFamily.heading}",
            "fontWeight": "{fontWeights.semibold}",
            "lineHeight": "{lineHeights.lg}",
            "fontSize": "{fontSizes.6xl}",
            "letterSpacing": "{letterSpacings.md}",
            "paragraphSpacing": "",
            "textCase": "",
            "textDecoration": ""
          },
          "type": "typography"
        },
        "d1": {
          "value": {
            "fontFamily": "{fontFamily.heading}",
            "fontWeight": "{fontWeights.semibold}",
            "lineHeight": "{lineHeights.lg}",
            "fontSize": "{fontSizes.7xl}",
            "letterSpacing": "{letterSpacings.md}",
            "paragraphSpacing": "",
            "textCase": "",
            "textDecoration": ""
          },
          "type": "typography"
        }
      },
      "extralight": {
        "h6": {
          "value": {
            "fontFamily": "{fontFamily.heading}",
            "fontWeight": "{fontWeights.thin}",
            "lineHeight": "{lineHeights.sm}",
            "fontSize": "{fontSizes.lg}",
            "letterSpacing": "{letterSpacings.md}",
            "paragraphSpacing": "",
            "textCase": "",
            "textDecoration": ""
          },
          "type": "typography"
        },
        "h5": {
          "value": {
            "fontFamily": "{fontFamily.heading}",
            "fontWeight": "{fontWeights.thin}",
            "lineHeight": "{lineHeights.sm}",
            "fontSize": "{fontSizes.xl}",
            "letterSpacing": "{letterSpacings.md}",
            "paragraphSpacing": "",
            "textCase": "",
            "textDecoration": ""
          },
          "type": "typography"
        },
        "h4": {
          "value": {
            "fontFamily": "{fontFamily.heading}",
            "fontWeight": "{fontWeights.thin}",
            "lineHeight": "{lineHeights.lg}",
            "fontSize": "{fontSizes.2xl}",
            "letterSpacing": "{letterSpacings.md}",
            "paragraphSpacing": "",
            "textCase": "",
            "textDecoration": ""
          },
          "type": "typography"
        },
        "h3": {
          "value": {
            "fontFamily": "{fontFamily.heading}",
            "fontWeight": "{fontWeights.thin}",
            "lineHeight": "{lineHeights.lg}",
            "fontSize": "{fontSizes.3xl}",
            "letterSpacing": "{letterSpacings.md}",
            "paragraphSpacing": "",
            "textCase": "",
            "textDecoration": ""
          },
          "type": "typography"
        },
        "h2": {
          "value": {
            "fontFamily": "{fontFamily.heading}",
            "fontWeight": "{fontWeights.thin}",
            "lineHeight": "{lineHeights.lg}",
            "fontSize": "{fontSizes.4xl}",
            "letterSpacing": "{letterSpacings.md}",
            "paragraphSpacing": "",
            "textCase": "",
            "textDecoration": ""
          },
          "type": "typography"
        },
        "h1": {
          "value": {
            "fontFamily": "{fontFamily.heading}",
            "fontWeight": "{fontWeights.thin}",
            "lineHeight": "{lineHeights.lg}",
            "fontSize": "{fontSizes.5xl}",
            "letterSpacing": "{letterSpacings.md}",
            "paragraphSpacing": "",
            "textCase": "",
            "textDecoration": ""
          },
          "type": "typography"
        },
        "d2": {
          "value": {
            "fontFamily": "{fontFamily.heading}",
            "fontWeight": "{fontWeights.thin}",
            "lineHeight": "{lineHeights.lg}",
            "fontSize": "{fontSizes.6xl}",
            "letterSpacing": "{letterSpacings.md}",
            "paragraphSpacing": "",
            "textCase": "",
            "textDecoration": ""
          },
          "type": "typography"
        },
        "d1": {
          "value": {
            "fontFamily": "{fontFamily.heading}",
            "fontWeight": "{fontWeights.thin}",
            "lineHeight": "{lineHeights.lg}",
            "fontSize": "{fontSizes.7xl}",
            "letterSpacing": "{letterSpacings.md}",
            "paragraphSpacing": "",
            "textCase": "",
            "textDecoration": ""
          },
          "type": "typography"
        }
      }
    }
  },
  "body": {
    "text": {
      "regular": {
        "c2": {
          "value": {
            "fontFamily": "{fontFamily.body}",
            "fontWeight": "{fontWeights.normal}",
            "lineHeight": "{lineHeights.lg}",
            "fontSize": "{fontSizes.2xs}",
            "letterSpacing": "{letterSpacings.md}",
            "paragraphSpacing": "",
            "textCase": "",
            "textDecoration": ""
          },
          "type": "typography"
        },
        "c1": {
          "value": {
            "fontFamily": "{fontFamily.body}",
            "fontWeight": "{fontWeights.normal}",
            "lineHeight": "{lineHeights.lg}",
            "fontSize": "{fontSizes.xs}",
            "letterSpacing": "{letterSpacings.md}",
            "paragraphSpacing": "",
            "textCase": "",
            "textDecoration": ""
          },
          "type": "typography"
        },
        "b4": {
          "value": {
            "fontFamily": "{fontFamily.body}",
            "fontWeight": "{fontWeights.normal}",
            "lineHeight": "{lineHeights.lg}",
            "fontSize": "{fontSizes.sm}",
            "letterSpacing": "{letterSpacings.md}",
            "paragraphSpacing": "",
            "textCase": "",
            "textDecoration": ""
          },
          "type": "typography"
        },
        "b3": {
          "value": {
            "fontFamily": "{fontFamily.body}",
            "fontWeight": "{fontWeights.normal}",
            "lineHeight": "{lineHeights.lg}",
            "fontSize": "{fontSizes.base}",
            "letterSpacing": "{letterSpacings.md}",
            "paragraphSpacing": "",
            "textCase": "",
            "textDecoration": ""
          },
          "type": "typography"
        },
        "b2": {
          "value": {
            "fontFamily": "{fontFamily.body}",
            "fontWeight": "{fontWeights.normal}",
            "lineHeight": "{lineHeights.lg}",
            "fontSize": "{fontSizes.md}",
            "letterSpacing": "{letterSpacings.md}",
            "paragraphSpacing": "",
            "textCase": "",
            "textDecoration": ""
          },
          "type": "typography"
        },
        "b1": {
          "value": {
            "fontFamily": "{fontFamily.body}",
            "fontWeight": "{fontWeights.normal}",
            "lineHeight": "{lineHeights.lg}",
            "fontSize": "{fontSizes.lg}",
            "letterSpacing": "{letterSpacings.md}",
            "paragraphSpacing": "",
            "textCase": "",
            "textDecoration": ""
          },
          "type": "typography"
        }
      },
      "bold": {
        "c2": {
          "value": {
            "fontFamily": "{fontFamily.body}",
            "fontWeight": "{fontWeights.semibold}",
            "lineHeight": "{lineHeights.lg}",
            "fontSize": "{fontSizes.2xs}",
            "letterSpacing": "{letterSpacings.md}",
            "paragraphSpacing": "",
            "textCase": "",
            "textDecoration": ""
          },
          "type": "typography"
        },
        "c1": {
          "value": {
            "fontFamily": "{fontFamily.body}",
            "fontWeight": "{fontWeights.semibold}",
            "lineHeight": "{lineHeights.lg}",
            "fontSize": "{fontSizes.xs}",
            "letterSpacing": "{letterSpacings.md}",
            "paragraphSpacing": "",
            "textCase": "",
            "textDecoration": ""
          },
          "type": "typography"
        },
        "b4": {
          "value": {
            "fontFamily": "{fontFamily.body}",
            "fontWeight": "{fontWeights.semibold}",
            "lineHeight": "{lineHeights.lg}",
            "fontSize": "{fontSizes.sm}",
            "letterSpacing": "{letterSpacings.md}",
            "paragraphSpacing": "",
            "textCase": "",
            "textDecoration": ""
          },
          "type": "typography"
        },
        "b3": {
          "value": {
            "fontFamily": "{fontFamily.body}",
            "fontWeight": "{fontWeights.semibold}",
            "lineHeight": "{lineHeights.lg}",
            "fontSize": "{fontSizes.base}",
            "letterSpacing": "{letterSpacings.md}",
            "paragraphSpacing": "",
            "textCase": "",
            "textDecoration": ""
          },
          "type": "typography"
        },
        "b2": {
          "value": {
            "fontFamily": "{fontFamily.body}",
            "fontWeight": "{fontWeights.semibold}",
            "lineHeight": "{lineHeights.lg}",
            "fontSize": "{fontSizes.md}",
            "letterSpacing": "{letterSpacings.md}",
            "paragraphSpacing": "",
            "textCase": "",
            "textDecoration": ""
          },
          "type": "typography"
        },
        "b1": {
          "value": {
            "fontFamily": "{fontFamily.body}",
            "fontWeight": "{fontWeights.semibold}",
            "lineHeight": "{lineHeights.lg}",
            "fontSize": "{fontSizes.lg}",
            "letterSpacing": "{letterSpacings.md}",
            "paragraphSpacing": "",
            "textCase": "",
            "textDecoration": ""
          },
          "type": "typography"
        }
      }
    }
  },
  "desktop": {
    "heading-desktop": {
      "bold": {
        "h6": {
          "value": {
            "fontFamily": "{fontFamily.heading}",
            "fontWeight": "{fontWeights.semibold}",
            "lineHeight": "{lineHeights.sm}",
            "fontSize": "{fontSizes.lg}",
            "letterSpacing": "{letterSpacings.md}",
            "paragraphSpacing": "",
            "textCase": "",
            "textDecoration": ""
          },
          "type": "typography"
        },
        "h5": {
          "value": {
            "fontFamily": "{fontFamily.heading}",
            "fontWeight": "{fontWeights.semibold}",
            "lineHeight": "{lineHeights.sm}",
            "fontSize": "{fontSizes.xl}",
            "letterSpacing": "{letterSpacings.md}",
            "paragraphSpacing": "",
            "textCase": "",
            "textDecoration": ""
          },
          "type": "typography"
        },
        "h4": {
          "value": {
            "fontFamily": "{fontFamily.heading}",
            "fontWeight": "{fontWeights.semibold}",
            "lineHeight": "{lineHeights.lg}",
            "fontSize": "{fontSizes.2xl}",
            "letterSpacing": "{letterSpacings.md}",
            "paragraphSpacing": "",
            "textCase": "",
            "textDecoration": ""
          },
          "type": "typography"
        },
        "h3": {
          "value": {
            "fontFamily": "{fontFamily.heading}",
            "fontWeight": "{fontWeights.semibold}",
            "lineHeight": "{lineHeights.lg}",
            "fontSize": "{fontSizes.3xl}",
            "letterSpacing": "{letterSpacings.md}",
            "paragraphSpacing": "",
            "textCase": "",
            "textDecoration": ""
          },
          "type": "typography"
        },
        "h2": {
          "value": {
            "fontFamily": "{fontFamily.heading}",
            "fontWeight": "{fontWeights.semibold}",
            "lineHeight": "{lineHeights.lg}",
            "fontSize": "{fontSizes.4xl}",
            "letterSpacing": "{letterSpacings.md}",
            "paragraphSpacing": "",
            "textCase": "",
            "textDecoration": ""
          },
          "type": "typography"
        },
        "h1": {
          "value": {
            "fontFamily": "{fontFamily.heading}",
            "fontWeight": "{fontWeights.semibold}",
            "lineHeight": "{lineHeights.lg}",
            "fontSize": "{fontSizes.5xl}",
            "letterSpacing": "{letterSpacings.md}",
            "paragraphSpacing": "",
            "textCase": "",
            "textDecoration": ""
          },
          "type": "typography"
        },
        "d2": {
          "value": {
            "fontFamily": "{fontFamily.heading}",
            "fontWeight": "{fontWeights.semibold}",
            "lineHeight": "{lineHeights.lg}",
            "fontSize": "{fontSizes.6xl}",
            "letterSpacing": "{letterSpacings.md}",
            "paragraphSpacing": "",
            "textCase": "",
            "textDecoration": ""
          },
          "type": "typography"
        },
        "d1": {
          "value": {
            "fontFamily": "{fontFamily.heading}",
            "fontWeight": "{fontWeights.semibold}",
            "lineHeight": "{lineHeights.lg}",
            "fontSize": "{fontSizes.7xl}",
            "letterSpacing": "{letterSpacings.md}",
            "paragraphSpacing": "",
            "textCase": "",
            "textDecoration": ""
          },
          "type": "typography"
        }
      },
      "extralight": {
        "h6": {
          "value": {
            "fontFamily": "{fontFamily.heading}",
            "fontWeight": "{fontWeights.thin}",
            "lineHeight": "{lineHeights.sm}",
            "fontSize": "{fontSizes.lg}",
            "letterSpacing": "{letterSpacings.md}",
            "paragraphSpacing": "",
            "textCase": "",
            "textDecoration": ""
          },
          "type": "typography"
        },
        "h5": {
          "value": {
            "fontFamily": "{fontFamily.heading}",
            "fontWeight": "{fontWeights.thin}",
            "lineHeight": "{lineHeights.sm}",
            "fontSize": "{fontSizes.xl}",
            "letterSpacing": "{letterSpacings.md}",
            "paragraphSpacing": "",
            "textCase": "",
            "textDecoration": ""
          },
          "type": "typography"
        },
        "h4": {
          "value": {
            "fontFamily": "{fontFamily.heading}",
            "fontWeight": "{fontWeights.thin}",
            "lineHeight": "{lineHeights.lg}",
            "fontSize": "{fontSizes.2xl}",
            "letterSpacing": "{letterSpacings.md}",
            "paragraphSpacing": "",
            "textCase": "",
            "textDecoration": ""
          },
          "type": "typography"
        },
        "h3": {
          "value": {
            "fontFamily": "{fontFamily.heading}",
            "fontWeight": "{fontWeights.thin}",
            "lineHeight": "{lineHeights.lg}",
            "fontSize": "{fontSizes.3xl}",
            "letterSpacing": "{letterSpacings.md}",
            "paragraphSpacing": "",
            "textCase": "",
            "textDecoration": ""
          },
          "type": "typography"
        },
        "h2": {
          "value": {
            "fontFamily": "{fontFamily.heading}",
            "fontWeight": "{fontWeights.thin}",
            "lineHeight": "{lineHeights.lg}",
            "fontSize": "{fontSizes.4xl}",
            "letterSpacing": "{letterSpacings.md}",
            "paragraphSpacing": "",
            "textCase": "",
            "textDecoration": ""
          },
          "type": "typography"
        },
        "h1": {
          "value": {
            "fontFamily": "{fontFamily.heading}",
            "fontWeight": "{fontWeights.thin}",
            "lineHeight": "{lineHeights.lg}",
            "fontSize": "{fontSizes.5xl}",
            "letterSpacing": "{letterSpacings.md}",
            "paragraphSpacing": "",
            "textCase": "",
            "textDecoration": ""
          },
          "type": "typography"
        },
        "d2": {
          "value": {
            "fontFamily": "{fontFamily.heading}",
            "fontWeight": "{fontWeights.thin}",
            "lineHeight": "{lineHeights.lg}",
            "fontSize": "{fontSizes.6xl}",
            "letterSpacing": "{letterSpacings.md}",
            "paragraphSpacing": "",
            "textCase": "",
            "textDecoration": ""
          },
          "type": "typography"
        },
        "d1": {
          "value": {
            "fontFamily": "{fontFamily.heading}",
            "fontWeight": "{fontWeights.thin}",
            "lineHeight": "{lineHeights.lg}",
            "fontSize": "{fontSizes.7xl}",
            "letterSpacing": "{letterSpacings.md}",
            "paragraphSpacing": "",
            "textCase": "",
            "textDecoration": ""
          },
          "type": "typography"
        }
      }
    }
  }
}